pymoas
