Metadata-Version: 2.1
Name: pymoas
Version: 0.24
Summary: short def
Home-page: UNKNOWN
Author-email: ivan.selyakovich@gmail.com
License: UNKNOWN
Platform: UNKNOWN
